MsgBot/__init__.py
MsgBot/ding_talk_bot/__init__.py
MsgBot/ding_talk_bot/bot.py
MsgBot/exceptions.py
MsgBot/wx_com_bot/__init__.py
MsgBot/wx_com_bot/bot.py
msgbot-0.1.3.dist-info/LICENSE
msgbot-0.1.3.dist-info/METADATA
msgbot-0.1.3.dist-info/WHEEL
msgbot-0.1.3.dist-info/RECORD
