Metadata-Version: 2.1
Name: msgbot
Version: 0.1.3
Summary: Python 实现的一个消息通知助手。可以使用钉钉群聊天机器人或者微信。
License: MIT
Author: maida
Requires-Python: >=3.12,<4.0
Classifier: License :: OSI Approved :: MIT License
Classifier: Programming Language :: Python :: 3
Classifier: Programming Language :: Python :: 3.12
